<?xml version="1.0" encoding="utf-8" ?>
<dwsync>
<file name="edita_conteudo_profissionais.php" server="200.169.230.165/public_html/" local="129798588600000000" remote="129798588600000000" Dst="-1" />
<file name="edita_conteudo_servico1.php" server="200.169.230.165/public_html/" local="129798588600000000" remote="129798588600000000" Dst="-1" />
<file name="edita_conteudo_servico2.php" server="200.169.230.165/public_html/" local="129798588600000000" remote="129798588600000000" Dst="-1" />
<file name="edita_conteudo_servico3.php" server="200.169.230.165/public_html/" local="129798588600000000" remote="129798588600000000" Dst="-1" />
<file name="edita_conteudo_servico4.php" server="200.169.230.165/public_html/" local="129798588600000000" remote="129798588600000000" Dst="-1" />
<file name="edita_depoimento.php" server="200.169.230.165/public_html/" local="129798588600000000" remote="129798588600000000" Dst="-1" />
<file name="edita_empresa.php" server="200.169.230.165/public_html/" local="129798588600000000" remote="129798588600000000" Dst="-1" />
<file name="edita_fotos_depoimentos.php" server="200.169.230.165/public_html/" local="129798588600000000" remote="129798588600000000" Dst="-1" />
<file name="edita_fotos_empresa.php" server="200.169.230.165/public_html/" local="129798588600000000" remote="129798588600000000" Dst="-1" />
<file name="edita_fotos_principal.php" server="200.169.230.165/public_html/" local="129798588600000000" remote="129798588600000000" Dst="-1" />
<file name="edita_fotos_profissionais.php" server="200.169.230.165/public_html/" local="129798588600000000" remote="129798588600000000" Dst="-1" />
<file name="edita_fotos_servicos.php" server="200.169.230.165/public_html/" local="129798588600000000" remote="129798588600000000" Dst="-1" />
<file name="edita_slide.php" server="200.169.230.165/public_html/" local="129798588600000000" remote="129798588600000000" Dst="-1" />
<file name="edita_upload_foto_conteudo_servico1.php" server="200.169.230.165/public_html/" local="129798588600000000" remote="129798588600000000" Dst="-1" />
<file name="edita_upload_foto_conteudo_servico2.php" server="200.169.230.165/public_html/" local="129798588600000000" remote="129798588600000000" Dst="-1" />
<file name="edita_upload_foto_conteudo_servico3.php" server="200.169.230.165/public_html/" local="129798588600000000" remote="129798588600000000" Dst="-1" />
<file name="edita_upload_foto_conteudo_servico4.php" server="200.169.230.165/public_html/" local="129798588600000000" remote="129798588600000000" Dst="-1" />
<file name="edita_upload_foto_profissionais.php" server="200.169.230.165/public_html/" local="129798588600000000" remote="129798588600000000" Dst="-1" />
<file name="edita_conteudo_profissionais.php" server="ftp.novaz.com.br/public_html/" local="129798588600000000" remote="129800774400000000" Dst="-1" />
<file name="edita_conteudo_servico1.php" server="ftp.novaz.com.br/public_html/" local="129798588600000000" remote="129800774400000000" Dst="-1" />
<file name="edita_conteudo_servico2.php" server="ftp.novaz.com.br/public_html/" local="129798588600000000" remote="129800774400000000" Dst="-1" />
<file name="edita_conteudo_servico3.php" server="ftp.novaz.com.br/public_html/" local="129798588600000000" remote="129800774400000000" Dst="-1" />
<file name="edita_conteudo_servico4.php" server="ftp.novaz.com.br/public_html/" local="129798588600000000" remote="131031420600000000" Dst="1" />
<file name="edita_depoimento.php" server="ftp.novaz.com.br/public_html/" local="129798588600000000" remote="131031420600000000" Dst="1" />
<file name="edita_empresa.php" server="ftp.novaz.com.br/public_html/" local="129798588600000000" remote="131031420600000000" Dst="1" />
<file name="edita_fotos_depoimentos.php" server="ftp.novaz.com.br/public_html/" local="129798588600000000" remote="131031420600000000" Dst="1" />
<file name="edita_fotos_empresa.php" server="ftp.novaz.com.br/public_html/" local="129798588600000000" remote="131031420600000000" Dst="1" />
<file name="edita_fotos_principal.php" server="ftp.novaz.com.br/public_html/" local="129798588600000000" remote="131031420600000000" Dst="1" />
<file name="edita_fotos_profissionais.php" server="ftp.novaz.com.br/public_html/" local="129798588600000000" remote="131031420600000000" Dst="1" />
<file name="edita_fotos_servicos.php" server="ftp.novaz.com.br/public_html/" local="129798588600000000" remote="131031420600000000" Dst="1" />
<file name="edita_slide.php" server="ftp.novaz.com.br/public_html/" local="129798588600000000" remote="131031420600000000" Dst="1" />
<file name="edita_upload_foto_conteudo_servico1.php" server="ftp.novaz.com.br/public_html/" local="129798588600000000" remote="131031420600000000" Dst="1" />
<file name="edita_upload_foto_conteudo_servico2.php" server="ftp.novaz.com.br/public_html/" local="129798588600000000" remote="131031420600000000" Dst="1" />
<file name="edita_upload_foto_conteudo_servico3.php" server="ftp.novaz.com.br/public_html/" local="129798588600000000" remote="131031420600000000" Dst="1" />
<file name="edita_upload_foto_conteudo_servico4.php" server="ftp.novaz.com.br/public_html/" local="129798588600000000" remote="131031420600000000" Dst="1" />
<file name="edita_upload_foto_profissionais.php" server="ftp.novaz.com.br/public_html/" local="129798588600000000" remote="131031420600000000" Dst="1" />
<file name="edita_conteudo_profissionais.php" server="177.85.98.170/public_html/" local="129798588600000000" remote="131181592800000000" Dst="1" />
<file name="edita_conteudo_servico1.php" server="177.85.98.170/public_html/" local="129798588600000000" remote="131181592800000000" Dst="1" />
<file name="edita_conteudo_servico2.php" server="177.85.98.170/public_html/" local="129798588600000000" remote="131181592800000000" Dst="1" />
<file name="edita_conteudo_servico3.php" server="177.85.98.170/public_html/" local="129798588600000000" remote="131181592800000000" Dst="1" />
<file name="edita_conteudo_servico4.php" server="177.85.98.170/public_html/" local="129798588600000000" remote="131181592800000000" Dst="1" />
<file name="edita_depoimento.php" server="177.85.98.170/public_html/" local="129798588600000000" remote="131181592800000000" Dst="1" />
<file name="edita_empresa.php" server="177.85.98.170/public_html/" local="129798588600000000" remote="131181592800000000" Dst="1" />
<file name="edita_fotos_depoimentos.php" server="177.85.98.170/public_html/" local="129798588600000000" remote="131181592800000000" Dst="1" />
<file name="edita_fotos_empresa.php" server="177.85.98.170/public_html/" local="129798588600000000" remote="131181592800000000" Dst="1" />
<file name="edita_fotos_principal.php" server="177.85.98.170/public_html/" local="129798588600000000" remote="131181592800000000" Dst="1" />
<file name="edita_fotos_profissionais.php" server="177.85.98.170/public_html/" local="129798588600000000" remote="131181592800000000" Dst="1" />
<file name="edita_fotos_servicos.php" server="177.85.98.170/public_html/" local="129798588600000000" remote="131181593400000000" Dst="1" />
<file name="edita_slide.php" server="177.85.98.170/public_html/" local="129798588600000000" remote="131181593400000000" Dst="1" />
<file name="edita_upload_foto_conteudo_servico1.php" server="177.85.98.170/public_html/" local="129798588600000000" remote="131181593400000000" Dst="1" />
<file name="edita_upload_foto_conteudo_servico2.php" server="177.85.98.170/public_html/" local="129798588600000000" remote="131181593400000000" Dst="1" />
<file name="edita_upload_foto_conteudo_servico3.php" server="177.85.98.170/public_html/" local="129798588600000000" remote="131181593400000000" Dst="1" />
<file name="edita_upload_foto_conteudo_servico4.php" server="177.85.98.170/public_html/" local="129798588600000000" remote="131181593400000000" Dst="1" />
<file name="edita_upload_foto_profissionais.php" server="177.85.98.170/public_html/" local="129798588600000000" remote="131181593400000000" Dst="1" />
</dwsync>