<?xml version="1.0" encoding="utf-8" ?>
<dwsync>
<file name="imagem_1334140228.jpg" server="200.169.230.165/public_html/" local="129798598200000000" remote="129798598200000000" Dst="-1" />
<file name="imagem_1334140326.jpg" server="200.169.230.165/public_html/" local="129798598200000000" remote="129798598200000000" Dst="-1" />
<file name="imagem_1334140355.jpg" server="200.169.230.165/public_html/" local="129798598200000000" remote="129798598200000000" Dst="-1" />
<file name="imagem_1334140406.jpg" server="200.169.230.165/public_html/" local="129798598800000000" remote="129798598800000000" Dst="-1" />
<file name="imagem_1334140442.jpg" server="200.169.230.165/public_html/" local="129798598800000000" remote="129798598800000000" Dst="-1" />
<file name="imagem_1334140504.jpg" server="200.169.230.165/public_html/" local="129798598800000000" remote="129798598800000000" Dst="-1" />
<file name="imagem_1334140539.jpg" server="200.169.230.165/public_html/" local="129798598800000000" remote="129798598800000000" Dst="-1" />
<file name="imagem_1334140566.jpg" server="200.169.230.165/public_html/" local="129798598800000000" remote="129798598800000000" Dst="-1" />
<file name="imagem_1334140622.jpg" server="200.169.230.165/public_html/" local="129798598800000000" remote="129798598800000000" Dst="-1" />
<file name="imagem_1334140627.jpg" server="200.169.230.165/public_html/" local="129798598800000000" remote="129798598800000000" Dst="-1" />
<file name="imagem_1334140663.jpg" server="200.169.230.165/public_html/" local="129798598800000000" remote="129798598800000000" Dst="-1" />
<file name="imagem_1334140680.jpg" server="200.169.230.165/public_html/" local="129798598800000000" remote="129798598800000000" Dst="-1" />
<file name="imagem_1334140686.jpg" server="200.169.230.165/public_html/" local="129798598800000000" remote="129798598800000000" Dst="-1" />
<file name="imagem_1334140691.jpg" server="200.169.230.165/public_html/" local="129798598800000000" remote="129798598800000000" Dst="-1" />
<file name="imagem_1334140722.jpg" server="200.169.230.165/public_html/" local="129798598800000000" remote="129798598800000000" Dst="-1" />
<file name="imagem_1334140751.jpg" server="200.169.230.165/public_html/" local="129798598800000000" remote="129798598800000000" Dst="-1" />
<file name="imagem_1334140758.jpg" server="200.169.230.165/public_html/" local="129798598800000000" remote="129798598800000000" Dst="-1" />
<file name="imagem_1334140763.jpg" server="200.169.230.165/public_html/" local="129798598800000000" remote="129798598800000000" Dst="-1" />
<file name="thumb_1334140228.jpg" server="200.169.230.165/public_html/" local="129798598800000000" remote="129798598800000000" Dst="-1" />
<file name="thumb_1334140326.jpg" server="200.169.230.165/public_html/" local="129798598800000000" remote="129798598800000000" Dst="-1" />
<file name="thumb_1334140355.jpg" server="200.169.230.165/public_html/" local="129798598800000000" remote="129798598800000000" Dst="-1" />
<file name="thumb_1334140406.jpg" server="200.169.230.165/public_html/" local="129798598800000000" remote="129798598800000000" Dst="-1" />
<file name="thumb_1334140442.jpg" server="200.169.230.165/public_html/" local="129798598800000000" remote="129798598800000000" Dst="-1" />
<file name="thumb_1334140504.jpg" server="200.169.230.165/public_html/" local="129798598800000000" remote="129798598800000000" Dst="-1" />
<file name="thumb_1334140539.jpg" server="200.169.230.165/public_html/" local="129798599400000000" remote="129798599400000000" Dst="-1" />
<file name="thumb_1334140566.jpg" server="200.169.230.165/public_html/" local="129798599400000000" remote="129798599400000000" Dst="-1" />
<file name="thumb_1334140622.jpg" server="200.169.230.165/public_html/" local="129798599400000000" remote="129798599400000000" Dst="-1" />
<file name="thumb_1334140627.jpg" server="200.169.230.165/public_html/" local="129798599400000000" remote="129798599400000000" Dst="-1" />
<file name="thumb_1334140663.jpg" server="200.169.230.165/public_html/" local="129798599400000000" remote="129798599400000000" Dst="-1" />
<file name="thumb_1334140680.jpg" server="200.169.230.165/public_html/" local="129798599400000000" remote="129798599400000000" Dst="-1" />
<file name="thumb_1334140686.jpg" server="200.169.230.165/public_html/" local="129798599400000000" remote="129798599400000000" Dst="-1" />
<file name="thumb_1334140691.jpg" server="200.169.230.165/public_html/" local="129798599400000000" remote="129798599400000000" Dst="-1" />
<file name="thumb_1334140722.jpg" server="200.169.230.165/public_html/" local="129798599400000000" remote="129798599400000000" Dst="-1" />
<file name="thumb_1334140751.jpg" server="200.169.230.165/public_html/" local="129798599400000000" remote="129798599400000000" Dst="-1" />
<file name="thumb_1334140758.jpg" server="200.169.230.165/public_html/" local="129798599400000000" remote="129798599400000000" Dst="-1" />
<file name="thumb_1334140763.jpg" server="200.169.230.165/public_html/" local="129798599400000000" remote="129798599400000000" Dst="-1" />
<file name="imagem_1334140228.jpg" server="ftp.novaz.com.br/public_html/" local="129798598200000000" remote="131031421800000000" Dst="1" />
<file name="imagem_1334140326.jpg" server="ftp.novaz.com.br/public_html/" local="129798598200000000" remote="131031421800000000" Dst="1" />
<file name="imagem_1334140355.jpg" server="ftp.novaz.com.br/public_html/" local="129798598200000000" remote="131031421800000000" Dst="1" />
<file name="imagem_1334140406.jpg" server="ftp.novaz.com.br/public_html/" local="129798598800000000" remote="131031421800000000" Dst="1" />
<file name="imagem_1334140442.jpg" server="ftp.novaz.com.br/public_html/" local="129798598800000000" remote="131031421800000000" Dst="1" />
<file name="imagem_1334140504.jpg" server="ftp.novaz.com.br/public_html/" local="129798598800000000" remote="131031421800000000" Dst="1" />
<file name="imagem_1334140539.jpg" server="ftp.novaz.com.br/public_html/" local="129798598800000000" remote="131031421800000000" Dst="1" />
<file name="imagem_1334140566.jpg" server="ftp.novaz.com.br/public_html/" local="129798598800000000" remote="131031421800000000" Dst="1" />
<file name="imagem_1334140622.jpg" server="ftp.novaz.com.br/public_html/" local="129798598800000000" remote="131031421800000000" Dst="1" />
<file name="imagem_1334140627.jpg" server="ftp.novaz.com.br/public_html/" local="129798598800000000" remote="131031421800000000" Dst="1" />
<file name="imagem_1334140663.jpg" server="ftp.novaz.com.br/public_html/" local="129798598800000000" remote="131031421800000000" Dst="1" />
<file name="imagem_1334140680.jpg" server="ftp.novaz.com.br/public_html/" local="129798598800000000" remote="131031421800000000" Dst="1" />
<file name="imagem_1334140686.jpg" server="ftp.novaz.com.br/public_html/" local="129798598800000000" remote="131031421800000000" Dst="1" />
<file name="imagem_1334140691.jpg" server="ftp.novaz.com.br/public_html/" local="129798598800000000" remote="131031421800000000" Dst="1" />
<file name="imagem_1334140722.jpg" server="ftp.novaz.com.br/public_html/" local="129798598800000000" remote="131031421800000000" Dst="1" />
<file name="imagem_1334140751.jpg" server="ftp.novaz.com.br/public_html/" local="129798598800000000" remote="131031421800000000" Dst="1" />
<file name="imagem_1334140758.jpg" server="ftp.novaz.com.br/public_html/" local="129798598800000000" remote="131031421800000000" Dst="1" />
<file name="imagem_1334140763.jpg" server="ftp.novaz.com.br/public_html/" local="129798598800000000" remote="131031422400000000" Dst="1" />
<file name="thumb_1334140228.jpg" server="ftp.novaz.com.br/public_html/" local="129798598800000000" remote="131031421800000000" Dst="1" />
<file name="thumb_1334140326.jpg" server="ftp.novaz.com.br/public_html/" local="129798598800000000" remote="131031421800000000" Dst="1" />
<file name="thumb_1334140355.jpg" server="ftp.novaz.com.br/public_html/" local="129798598800000000" remote="131031421800000000" Dst="1" />
<file name="thumb_1334140406.jpg" server="ftp.novaz.com.br/public_html/" local="129798598800000000" remote="131031422400000000" Dst="1" />
<file name="thumb_1334140442.jpg" server="ftp.novaz.com.br/public_html/" local="129798598800000000" remote="131031422400000000" Dst="1" />
<file name="thumb_1334140504.jpg" server="ftp.novaz.com.br/public_html/" local="129798598800000000" remote="131031422400000000" Dst="1" />
<file name="thumb_1334140539.jpg" server="ftp.novaz.com.br/public_html/" local="129798599400000000" remote="131031422400000000" Dst="1" />
<file name="thumb_1334140566.jpg" server="ftp.novaz.com.br/public_html/" local="129798599400000000" remote="131031422400000000" Dst="1" />
<file name="thumb_1334140622.jpg" server="ftp.novaz.com.br/public_html/" local="129798599400000000" remote="131031422400000000" Dst="1" />
<file name="thumb_1334140627.jpg" server="ftp.novaz.com.br/public_html/" local="129798599400000000" remote="131031422400000000" Dst="1" />
<file name="thumb_1334140663.jpg" server="ftp.novaz.com.br/public_html/" local="129798599400000000" remote="131031422400000000" Dst="1" />
<file name="thumb_1334140680.jpg" server="ftp.novaz.com.br/public_html/" local="129798599400000000" remote="131031422400000000" Dst="1" />
<file name="thumb_1334140686.jpg" server="ftp.novaz.com.br/public_html/" local="129798599400000000" remote="131031422400000000" Dst="1" />
<file name="thumb_1334140691.jpg" server="ftp.novaz.com.br/public_html/" local="129798599400000000" remote="131031422400000000" Dst="1" />
<file name="thumb_1334140722.jpg" server="ftp.novaz.com.br/public_html/" local="129798599400000000" remote="131031422400000000" Dst="1" />
<file name="thumb_1334140751.jpg" server="ftp.novaz.com.br/public_html/" local="129798599400000000" remote="131031422400000000" Dst="1" />
<file name="thumb_1334140758.jpg" server="ftp.novaz.com.br/public_html/" local="129798599400000000" remote="131031422400000000" Dst="1" />
<file name="thumb_1334140763.jpg" server="ftp.novaz.com.br/public_html/" local="129798599400000000" remote="131031422400000000" Dst="1" />
</dwsync>